ez_azml-0.1.4.dist-info/METADATA
ez_azml-0.1.4.dist-info/WHEEL
ez_azml-0.1.4.dist-info/entry_points.txt
ez_azml/__init__.py
ez_azml/__version__.py
ez_azml/cli/__init__.py
ez_azml/cli/ez_azml.py
ez_azml/cli/main.py
ez_azml/cloud_runs/__init__.py
ez_azml/cloud_runs/cloud_run.py
ez_azml/cloud_runs/commands/__init__.py
ez_azml/cloud_runs/commands/command.py
ez_azml/cloud_runs/commands/docker_command.py
ez_azml/cloud_runs/pipelines/__init__.py
ez_azml/cloud_runs/pipelines/pipeline.py
ez_azml/entities/__init__.py
ez_azml/entities/compute.py
ez_azml/entities/environments.py
ez_azml/entities/workspace.py
ez_azml/env.py
ez_azml/ml_client.py
ez_azml/params.py
ez_azml-0.1.4.dist-info/RECORD
