Metadata-Version: 2.1
Name: ez-azml
Version: 0.1.4
Summary: Simplified yaml/jsonargparse driven framework for AzureML interactions
Author-Email: =?utf-8?q?Alejandro_Bar=C3=B3n?= <alejandrobarongarcia10@gmail.com>
License: MIT
Requires-Python: >=3.9
Requires-Dist: jsonargparse>=4.32.0
Requires-Dist: azure-ai-ml>=1.18.0
Requires-Dist: azure-identity>=1.17.1
Requires-Dist: loguru>=0.7.2
Requires-Dist: mldesigner>=0.1.0b18
Requires-Dist: setuptools>=72.1.0
